textagon/Scripts/Activate.ps1
textagon/Scripts/activate
textagon/Scripts/activate.bat
textagon/Scripts/deactivate.bat
textagon/Scripts/f2py.exe
textagon/Scripts/get_objgraph
textagon/Scripts/nltk.exe
textagon/Scripts/normalizer.exe
textagon/Scripts/pathos_connect
textagon/Scripts/pathy.exe
textagon/Scripts/pip.exe
textagon/Scripts/pip3.9.exe
textagon/Scripts/pip3.exe
textagon/Scripts/portpicker
textagon/Scripts/pox
textagon/Scripts/ppserver
textagon/Scripts/python.exe
textagon/Scripts/pythonw.exe
textagon/Scripts/spacy.exe
textagon/Scripts/textagon_post_install-script.py
textagon/Scripts/textagon_post_install.exe
textagon/Scripts/tqdm.exe
textagon/Scripts/undill
textagon/__init__.py
textagon/customwna.py
textagon/data/Lexicons_v5.zip
textagon/data/sentiscores.txt
textagon/data/wn-domains/Coling-04-ws-WDH.pdf
textagon/data/wn-domains/README
textagon/data/wn-domains/WDH-old-new-comparison.pdf
textagon/data/wn-domains/WDH-revision-summary.pdf
textagon/data/wn-domains/WDH-to-DDC-map.pdf
textagon/data/wn-domains/WORDNET-DOMAINS-2.0-TR.pdf
textagon/data/wn-domains/version-history.txt
textagon/data/wn-domains/wn-affect-1.0/wn-affect-labels-1.0.txt
textagon/data/wn-domains/wn-affect-1.0/wn-affect-legenda-1.0.txt
textagon/data/wn-domains/wn-affect-1.1/a-hierarchy.xml
textagon/data/wn-domains/wn-affect-1.1/a-synsets.xml
textagon/data/wn-domains/wn-affect-1.1/readme-wn-affect-1.1.txt
textagon/data/wn-domains/wn-domains-2.0-20050210
textagon/data/wn-domains/wn-domains-3.2-20070223
textagon/data/wordnet-1.6/CHANGES
textagon/data/wordnet-1.6/INSTALL
textagon/data/wordnet-1.6/LICENSE
textagon/data/wordnet-1.6/Makefile
textagon/data/wordnet-1.6/README
textagon/data/wordnet-1.6/README.ml
textagon/data/wordnet-1.6/README.tcltk
textagon/data/wordnet-1.6/bin/Makefile
textagon/data/wordnet-1.6/bin/irix/Makefile
textagon/data/wordnet-1.6/bin/irix/wishwn
textagon/data/wordnet-1.6/bin/irix/wn
textagon/data/wordnet-1.6/bin/irix/wnb
textagon/data/wordnet-1.6/bin/linux/Makefile
textagon-0.3.0.dist-info/LICENSE
textagon-0.3.0.dist-info/METADATA
textagon-0.3.0.dist-info/WHEEL
textagon-0.3.0.dist-info/RECORD
