Metadata-Version: 2.3
Name: textagon
Version: 0.3.0
Summary: Textagon is a powerful tool for text data analysis, providing a means to visualize parallel representations of your data and gain insight into the impact of various lexicons on two classes of text data.
License: MIT
Author: John P. Lalor
Author-email: john.lalor@nd.edu
Requires-Python: >=3.10,<4.0
Classifier: License :: OSI Approved :: MIT License
Classifier: Programming Language :: Python :: 3
Classifier: Programming Language :: Python :: 3.10
Classifier: Programming Language :: Python :: 3.11
Classifier: Programming Language :: Python :: 3.12
Classifier: Programming Language :: Python :: 3.13
Requires-Dist: beautifulsoup4 (>=4.11.2)
Requires-Dist: mapply (>=0.1.21)
Requires-Dist: nltk (>=3.8.1)
Requires-Dist: numpy (>=1.24.2,<2.0.0)
Requires-Dist: pandas (>=1.5.3)
Requires-Dist: pyenchant (>=3.2.2)
Requires-Dist: pywsd (>=1.2.5,<2.0.0)
Requires-Dist: scikit-learn (>=1.2.1)
Requires-Dist: spacy (>=3.5.2)
Requires-Dist: tzlocal (>=4.3)
Requires-Dist: wn (==0.0.23)
